mcp_service.py
ollama_websearch_mcp-0.1.3.dist-info/METADATA
ollama_websearch_mcp-0.1.3.dist-info/WHEEL
ollama_websearch_mcp-0.1.3.dist-info/entry_points.txt
ollama_websearch_mcp-0.1.3.dist-info/top_level.txt
ollama_websearch_mcp-0.1.3.dist-info/RECORD
