Metadata-Version: 2.4
Name: ollama-websearch-mcp
Version: 0.1.3
Summary: MCP Service for Ollama Web Search
Home-page: https://github.com/huangxinping/ollama-websearch-mcp
Author: huangxinping
Author-email: huangxinping <monor.huang@gmail.com>
License: MIT
Project-URL: Homepage, https://github.com/huangxinping/ollama-websearch-mcp
Project-URL: Repository, https://github.com/huangxinping/ollama-websearch-mcp
Project-URL: Issues, https://github.com/huangxinping/ollama-websearch-mcp/issues
Keywords: ollama,mcp,search,ai,web-search
Classifier: Development Status :: 3 - Alpha
Classifier: Intended Audience :: Developers
Classifier: License :: OSI Approved :: MIT License
Classifier: Programming Language :: Python :: 3
Classifier: Programming Language :: Python :: 3.12
Requires-Python: >=3.12
Requires-Dist: python-dotenv>=0.19.0
Requires-Dist: ollama>=0.6.0
Requires-Dist: mcp>=1.15.0
Dynamic: author
Dynamic: home-page
Dynamic: requires-python
